pymoran/__init__.py
pymoran/dbclient.py
pymoran/osstool.py
pymoran/ostool.py
pymoran/pictool.py
pymoran/strtool.py
pymoran/timetool.py
pymoran/webtool.py
pymoran-0.0.40.dist-info/LICENSE
pymoran-0.0.40.dist-info/METADATA
pymoran-0.0.40.dist-info/WHEEL
pymoran-0.0.40.dist-info/top_level.txt
pymoran-0.0.40.dist-info/RECORD
