Metadata-Version: 2.1
Name: pymoran
Version: 0.0.40
Summary: 简单的自用包
Author: Moran
Author-email: wqmoran@163.com
Classifier: Programming Language :: Python :: 3
Classifier: License :: OSI Approved :: MIT License
Classifier: Operating System :: OS Independent
Requires-Python: >=3.6
License-File: LICENSE
